hello_earth/__init__.py
hello_earth/main.py
hello_earth-1.3.0.dist-info/METADATA
hello_earth-1.3.0.dist-info/WHEEL
hello_earth-1.3.0.dist-info/top_level.txt
hello_earth-1.3.0.dist-info/RECORD
