Metadata-Version: 2.1
Name: hello_earth
Version: 1.3.0
